stem_registration/__init__.py
stem_registration/admin.py
stem_registration/apps.py
stem_registration/forms.py
stem_registration/models.py
stem_registration/urls.py
stem_registration/views.py
stem_registration/locale/ru/LC_MESSAGES/django.mo
stem_registration/locale/ru/LC_MESSAGES/django.po
stem_registration/locale/uk/LC_MESSAGES/django.mo
stem_registration/locale/uk/LC_MESSAGES/django.po
stem_registration/migrations/0001_initial.py
stem_registration/migrations/0002_auto_20181031_1101.py
stem_registration/migrations/0003_auto_20181031_1302.py
stem_registration/migrations/0004_auto_20181107_1205.py
stem_registration/migrations/0005_auto_20181112_1728.py
stem_registration/migrations/0006_auto_20181115_1626.py
stem_registration/migrations/0007_auto_20181116_1818.py
stem_registration/migrations/__init__.py
stem_registration/static/stem_registration/css/style.css
stem_registration/static/stem_registration/img/logo.svg
stem_registration/static/stem_registration/js/base.js
stem_registration/static/stem_registration/js/dist/jquery.inputmask.bundle.js
stem_registration/static/stem_registration/js/dist/inputmask/inputmask.date.extensions.js
stem_registration/static/stem_registration/js/dist/inputmask/inputmask.extensions.js
stem_registration/static/stem_registration/js/dist/inputmask/inputmask.js
stem_registration/static/stem_registration/js/dist/inputmask/inputmask.numeric.extensions.js
stem_registration/static/stem_registration/js/dist/inputmask/inputmask.phone.extensions.js
stem_registration/static/stem_registration/js/dist/inputmask/inputmask.regex.extensions.js
stem_registration/static/stem_registration/js/dist/inputmask/jquery.inputmask.js
stem_registration/static/stem_registration/js/dist/inputmask/bindings/inputmask.binding.js
stem_registration/static/stem_registration/js/dist/inputmask/dependencyLibs/inputmask.dependencyLib.jqlite.js
stem_registration/static/stem_registration/js/dist/inputmask/dependencyLibs/inputmask.dependencyLib.jquery.js
stem_registration-0.0.49.dist-info/LICENSE
stem_registration-0.0.49.dist-info/METADATA
stem_registration-0.0.49.dist-info/WHEEL
stem_registration-0.0.49.dist-info/top_level.txt
stem_registration-0.0.49.dist-info/RECORD
