Metadata-Version: 2.1
Name: stem-registration
Version: 0.0.49
Summary: A small registration package
Home-page: https://gitlab.stemsc.com/shevelev/registration
Author: Dmitry Shevelev
Author-email: shevelev.dmitriy@stemsc.com
License: UNKNOWN
Platform: UNKNOWN
Classifier: Programming Language :: Python :: 3
Classifier: License :: OSI Approved :: MIT License
Classifier: Operating System :: OS Independent
Requires-Dist: django (<2,>=1.11)
Requires-Dist: Pillow (>=5.3.0)
Requires-Dist: django-registration-redux (>=2.4)
Requires-Dist: django-bootstrap4 (>=0.0.6)
Requires-Dist: django-cities-light (>=3.5.0)
Requires-Dist: django-select2 (>=6.3.1)
